githubtakeout.py
progress.py
githubtakeout-0.1.20.dist-info/licenses/LICENSE
githubtakeout-0.1.20.dist-info/METADATA
githubtakeout-0.1.20.dist-info/WHEEL
githubtakeout-0.1.20.dist-info/entry_points.txt
githubtakeout-0.1.20.dist-info/top_level.txt
githubtakeout-0.1.20.dist-info/RECORD
