Metadata-Version: 2.4
Name: githubtakeout
Version: 0.1.20
Summary: Backup and archive Git Repos and Gists from GitHub
Author: Corey Goldberg
Maintainer: Corey Goldberg
License-Expression: MIT
Project-URL: homepage, https://github.com/cgoldberg/githubtakeout
Project-URL: source, https://github.com/cgoldberg/githubtakeout
Project-URL: download, https://pypi.org/project/githubtakeout
Keywords: git,github,archive,backup,export,takeout
Classifier: Environment :: Console
Classifier: Intended Audience :: Developers
Classifier: Programming Language :: Python
Classifier: Programming Language :: Python :: 3
Classifier: Programming Language :: Python :: 3.12
Classifier: Programming Language :: Python :: 3.13
Classifier: Programming Language :: Python :: 3.14
Requires-Python: >=3.12
License-File: LICENSE
Requires-Dist: GitPython==3.1.46
Requires-Dist: PyGithub==2.8.1
Requires-Dist: python-dotenv==1.2.1
Requires-Dist: rich==14.2.0
Dynamic: license-file
